[
  {
    "Type": "StringTable",
    "Name": "ST_Fork",
    "Class": "UScriptClass'StringTable'",
    "Flags": "RF_Public | RF_Standalone | RF_Transactional | RF_WasLoaded | RF_LoadCompleted",
    "StringTable": {
      "TableNamespace": "ST_Fork",
      "KeysToEntries": {
        "fork_wushoutieyu_name": "焰魂狂飙",
        "fork_yuren_name": "勿忘伞",
        "fork_bopu_name": "光波眩晕，迷走狂欢",
        "fork_mofeikesi_name": "好狗狗走四方",
        "fork_jiaojuan_name": "闪耀的每一天",
        "fork_wuhuakuang_name": "被遗忘者",
        "fork_jingmotingyuan_name": "茶花会",
        "fork_oulaquantao_name": "欧拉欧拉！",
        "fork_lingganzhongjiezhe_name": "灵感大逃杀",
        "fork_rishi_name": "休息日",
        "fork_wushoutieyu_des": "流淌于吾之体内的是对速度的渴望、轰鸣于吾之胸腔的是引擎的咆哮！来吧，来吧！踏上这以速度之魂相赌的赛道！",
        "fork_yuren_des": "记得睡觉，记得看天气预报；记得吃饭，记得出门带伞。",
        "fork_bopu_des": "Masterpiece made by 「Pop Re-Creator 」!",
        "fork_mofeikesi_des": "你看到的是什么？长着翅膀的白狼？可爱的白色大狗？亦或是……？",
        "fork_jiaojuan_des": "捕捉闪耀的瞬间，在梦中都要继续。后悔从来都不会是美好的，你也并非是孤单一人。",
        "fork_wuhuakuang_des": "即使是那些传世作品的陪衬，但……我也是很漂亮的，对吗？",
        "fork_jingmotingyuan_des": "虽然不被允许把失态暴露在花瓣上……那句花可真是深深刺伤我了。",
        "fork_oulaquantao_des": "据说在遥远地方，欧拉拳套有一个远方表弟，叫做「木大拳套」。",
        "fork_lingganzhongjiezhe_des": "灵感像薯片，咔滋咔滋，留下一地碎屑，没有理由。",
        "fork_rishi_des": "日蚀说，要有双休。\n于是就有了双休（日蚀专属版）。",
        "fork_wushoutieyu_context": "来吧，来吧！踏上这以速度之魂相赌的赛道！",
        "fork_yuren_context": "记得睡觉，记得看天气预报；记得吃饭，记得出门带伞。",
        "fork_bopu_context": "Masterpiece made by 「Pop Re-Creator 」!",
        "fork_mofeikesi_context": "你看到的是什么？长着翅膀的白狼？可爱的白色大狗？亦或是……？",
        "fork_jiaojuan_context": "捕捉闪耀的瞬间，在梦中都要继续。",
        "fork_wuhuakuang_context": "即使是那些传世作品的陪衬，但……我也是很漂亮的，对吗？",
        "fork_jingmotingyuan_context": "虽然不被允许把失态暴露在花瓣上……那句花可真是深深刺伤我了。",
        "fork_oulaquantao_context": "据说在遥远地方，欧拉拳套有一个远方表弟，叫做「木大拳套」。",
        "fork_lingganzhongjiezhe_context": "灵感像薯片，咔滋咔滋，留下一地碎屑，没有理由。",
        "fork_rishi_context": "日蚀说，要有双休。",
        "buff_fork_wushoutieyu_name": "「无首铁驭」",
        "buff_fork_yuren_name": "「雨人」",
        "buff_fork_bopu_name": "「波普」",
        "buff_fork_mofeikesi_name": "「墨菲克斯」",
        "buff_fork_jiaojuan_name": "「胶卷-MANISHI」",
        "buff_fork_wuhuakuang_name": "「无画框」",
        "buff_fork_jingmotingyuan_name": "「静默庭园」",
        "buff_fork_oulaquantao_name": "「欧拉拳套」",
        "buff_fork_lingganzhongjiezhe_name": "「灵感终结者」",
        "buff_fork_rishi_name": "「日蚀」",
        "fork_dustbin_name": "危险游戏",
        "fork_nonos_name": "成功的第一步",
        "fork_vine_name": "笑口常开",
        "fork_Prokaryon_name": "我们。",
        "fork_tuansanlang_name": "该死的邂逅",
        "fork_BitterCake_name": "良药苦口",
        "fork_Kite_name": "当心头顶",
        "fork_PaperPlane_name": "开始净空",
        "fork_appliance_name": "「电音」狂欢",
        "fork_spider_name": "挂你在心口难开",
        "fork_yaodao_name": "拔刀",
        "fork_koinobori_name": "终有时",
        "fork_BitGame_name": "引爆全场",
        "fork_mamen_name": "思考喵",
        "fork_BlackBook_name": "漆黑青春妄想",
        "fork_Arachne_name": "永恒圆舞曲",
        "fork_PoliceRat_name": "海特洛的安宁",
        "fork_Nakupeda_name": "千金难买你开心",
        "fork_snowman_name": "愚者种春",
        "fork_TigerTally_name": "预备备",
        "fork_dustbin_des": "我跟你打个赌，输的人要吃土。",
        "fork_nonos_des": "优良的自我管理是走上成功道路的第一步。",
        "fork_vine_des": "嗯？你怎么不笑呢？",
        "fork_Prokaryon_des": "我是、你……是……你，是……它、是……我……不，我——是、我们。",
        "fork_tuansanlang_des": "见到你的第一眼，无法抗拒被夺走视线。柔软的毛发，脸上的狡黠，入迷许久，等到你离开后才发现——我烤串呢？",
        "fork_BitterCake_des": "些许的苦涩，但也会给你好心情，不是吗？",
        "fork_Kite_des": "嘻嘻嘻……别怕，不过是一只爱笑的风筝而已……",
        "fork_PaperPlane_des": "战斗队形已确认，准备夺取制空权。",
        "fork_appliance_des": "哪有电音？附电灵发出来的声音怎么不算「电音」呢？",
        "fork_spider_des": "当你在老师的眼睛里看到红光，那一般代表你要挂科了。",
        "fork_yaodao_des": "孤月，墨云。刃出，魂归。色褪，刃泣。",
        "fork_koinobori_des": "自天而下，重归于天。相信着那命中注定的一日，我们跃入这看不见终点的洄游。",
        "fork_BitGame_des": "嘘……要来了，要来了！要！来！！了！！！",
        "fork_mamen_des": "生命的意义……存在的理由……宇宙的答案是——4……毛线团！",
        "fork_BlackBook_des": "「秘密」——当它被记录下来的那一刻起，就已经被所有人看见了。",
        "fork_Arachne_des": "与我一同跳起3/4拍的舞步，感受仿佛世界末日般的晕眩感，直至永远！",
        "fork_PoliceRat_des": "再一次的，一天平安度过了。感谢巡哨鼠鼠的努力！",
        "fork_Nakupeda_des": "嗯，嗯嗯嗯，嗯嗯嗯嗯嗯嗯嗯嗯！（方斯给我，你开心，我也开心！）",
        "fork_snowman_des": "假如我是一只蝉，我也会用嘶哑的喉咙歌唱。",
        "fork_TigerTally_des": " 握住我，抱着超越死亡的勇气与决心——向您致敬，伟大的猛虎将士。",
        "fork_dustbin_context": "我跟你打个赌，输的人要吃土。",
        "fork_nonos_context": "优良的自我管理是走上成功道路的第一步。",
        "fork_vine_context": "嗯？你怎么不笑呢？",
        "fork_Prokaryon_context": "我是、你……是……你，是……它、是……我……不，我——是、我们。",
        "fork_tuansanlang_context": "见到你的第一眼，无法抗拒被夺走视线。柔软的毛发，脸上的狡黠，入迷许久，等到你离开后才发现——我烤串呢？",
        "fork_BitterCake_context": "些许的苦涩，但也会给你好心情，不是吗？",
        "fork_Kite_context": "嘻嘻嘻……别怕，不过是一只爱笑的风筝而已……",
        "fork_PaperPlane_context": "战斗队形已确认，准备夺取制空权。",
        "fork_appliance_context": "哪有电音？附电灵发出来的声音怎么不算「电音」呢？",
        "fork_spider_context": "当你在老师的眼睛里看到红光，那一般代表你要挂科了。",
        "fork_yaodao_context": "孤月，墨云。刃出，魂归。色褪，刃泣。",
        "fork_koinobori_context": "自天而下，重归于天。相信着那命中注定的一日，我们跃入这看不见终点的洄游。",
        "fork_BitGame_context": "嘘……要来了，要来了！要！来！！了！！！",
        "fork_mamen_context": "生命的意义……存在的理由……宇宙的答案是——4……毛线团！",
        "fork_BlackBook_context": "「秘密」——当它被记录下来的那一刻起，就已经被所有人看见了。",
        "fork_Arachne_context": "与我一同跳起3/4拍的舞步，感受仿佛世界末日般的晕眩感，直至永远！",
        "fork_PoliceRat_context": "再一次的，一天平安度过了。感谢巡哨鼠鼠的努力！",
        "fork_Nakupeda_context": "嗯，嗯嗯嗯，嗯嗯嗯嗯嗯嗯嗯嗯！（方斯给我，你开心，我也开心！）",
        "fork_snowman_context": "假如我是一只蝉，我也会用嘶哑的喉咙歌唱。",
        "fork_TigerTally_context": " 握住我，抱着超越死亡的勇气与决心——向您致敬，伟大的猛虎将士。",
        "buff_fork_yuren_effect1": "生命值提高<lv>12.00%</>。\n当装备者生命值高于50%的时候自身获得<lv>12.00%</>护盾强化。",
        "buff_fork_yuren_effect2": "生命值提高<lv>14.00%</>。\n当装备者生命值高于50%的时候自身获得<lv>14.00%</>护盾强化。",
        "buff_fork_yuren_effect3": "生命值提高<lv>16.00%</>。\n当装备者生命值高于50%的时候自身获得<lv>16.00%</>护盾强化。",
        "buff_fork_yuren_effect4": "生命值提高<lv>18.00%</>。\n当装备者生命值高于50%的时候自身获得<lv>18.00%</>护盾强化。",
        "buff_fork_yuren_effect5": "生命值提高<lv>20.00%</>。\n当装备者生命值高于50%的时候自身获得<lv>20.00%</>护盾强化。",
        "buff_fork_bopu_effect1": "装备者释放「协同技」后<lv>10</>秒内，造成的伤害提高<lv>20.00%</>。每<lv>20</>秒最多触发一次。",
        "buff_fork_bopu_effect2": "装备者释放「协同技」后<lv>10</>秒内，造成的伤害提高<lv>23.00%</>。每<lv>20</>秒最多触发一次。",
        "buff_fork_bopu_effect3": "装备者释放「协同技」后<lv>10</>秒内，造成的伤害提高<lv>26.00%</>。每<lv>20</>秒最多触发一次。",
        "buff_fork_bopu_effect4": "装备者释放「协同技」后<lv>10</>秒内，造成的伤害提高<lv>29.00%</>。每<lv>20</>秒最多触发一次。",
        "buff_fork_bopu_effect5": "装备者释放「协同技」后<lv>10</>秒内，造成的伤害提高<lv>32.00%</>。每<lv>20</>秒最多触发一次。",
        "buff_fork_mofeikesi_effect1": "蓄质速率提高<lv>20.00%</>。\n装备者释放「极轨终结」后<lv>20</>秒内，全队攻击力提高<lv>10.00%</>；若敌人受到该「极轨终结」的控制效果，全队额外提高<lv>5.00%</>攻击力。同名效果无法叠加。",
        "buff_fork_mofeikesi_effect2": "蓄质速率提高<lv>25.00%</>。\n装备者释放「极轨终结」后<lv>20</>秒内，全队攻击力提高<lv>12.50%</>；若敌人受到该「极轨终结」的控制效果，全队额外提高<lv>6.25%</>攻击力。同名效果无法叠加。",
        "buff_fork_mofeikesi_effect3": "蓄质速率提高<lv>30.00%</>。\n装备者释放「极轨终结」后<lv>20</>秒内，全队攻击力提高<lv>15.00%</>；若敌人受到该「极轨终结」的控制效果，全队额外提高<lv>7.50%</>攻击力。同名效果无法叠加。",
        "buff_fork_mofeikesi_effect4": "蓄质速率提高<lv>35.00%</>。\n装备者释放「极轨终结」后<lv>20</>秒内，全队攻击力提高<lv>17.50%</>；若敌人受到该「极轨终结」的控制效果，全队额外提高<lv>8.75%</>攻击力。同名效果无法叠加。",
        "buff_fork_mofeikesi_effect5": "蓄质速率提高<lv>40.00%</>。\n装备者释放「极轨终结」后<lv>20</>秒内，全队攻击力提高<lv>20.00%</>；若敌人受到该「极轨终结」的控制效果，全队额外提高<lv>10.00%</>攻击力。同名效果无法叠加。",
        "buff_fork_jiaojuan_effect1": "倾陷强度提高<lv>60</>。\n装备者攻击倾陷单位造成的伤害提高<lv>12.00%</>。",
        "buff_fork_jiaojuan_effect2": "倾陷强度提高<lv>69</>。\n装备者攻击倾陷单位造成的伤害提高<lv>14.00%</>。",
        "buff_fork_jiaojuan_effect3": "倾陷强度提高<lv>78</>。\n装备者攻击倾陷单位造成的伤害提高<lv>16.00%</>。",
        "buff_fork_jiaojuan_effect4": "倾陷强度提高<lv>87</>。\n装备者攻击倾陷单位造成的伤害提高<lv>18.00%</>。",
        "buff_fork_jiaojuan_effect5": "倾陷强度提高<lv>96</>。\n装备者攻击倾陷单位造成的伤害提高<lv>20.00%</>。",
        "buff_fork_wuhuakuang_effect1": "装备者生命值高于50%的时候攻击力提高<lv>25.00%</>；生命值低于50%的时候，防御力提高<lv>25.00%</>。",
        "buff_fork_wuhuakuang_effect2": "装备者生命值高于50%的时候攻击力提高<lv>28.00%</>；生命值低于50%的时候，防御力提高<lv>28.00%</>。",
        "buff_fork_wuhuakuang_effect3": "装备者生命值高于50%的时候攻击力提高<lv>32.00%</>；生命值低于50%的时候，防御力提高<lv>32.00%</>。",
        "buff_fork_wuhuakuang_effect4": "装备者生命值高于50%的时候攻击力提高<lv>36.00%</>；生命值低于50%的时候，防御力提高<lv>36.00%</>。",
        "buff_fork_wuhuakuang_effect5": "装备者生命值高于50%的时候攻击力提高<lv>40.00%</>；生命值低于50%的时候，防御力提高<lv>40.00%</>。",
        "buff_fork_jingmotingyuan_effect1": "装备者在未受到伤害的情况下降低血量后<lv>5</>秒内获得<lv>16.00%</>暴击伤害提高，至多叠加4次；可使用调弧·「静默庭园」\r\n调弧·「静默庭园」：扣除自身<lv>5.00%</>当前生命值，随机释放以下一种攻击（冷却时间<lv>25</>秒）：\r\n厉声呵斥：不留情面的呵斥如暴雨中的落叶接二连三，对目标造成5次<lv>24.00%</>攻击力的咒系伤害。\r\n喋喋不休：尖锐刻薄的话语如荆棘般不断刺穿目标，对目标连续造成6次基础伤害为<lv>16.00%</>攻击力的咒系伤害，最后一次攻击造成双倍伤害。",
        "buff_fork_jingmotingyuan_effect2": "装备者在未受到伤害的情况下降低血量后<lv>5</>秒内获得<lv>20.00%</>暴击伤害提高，至多叠加4次；可使用调弧·「静默庭园」\r\n调弧·「静默庭园」：扣除自身<lv>5.00%</>当前生命值，随机释放以下一种攻击（冷却时间<lv>25</>秒）：\r\n厉声呵斥：不留情面的呵斥如暴雨中的落叶接二连三，对目标造成5次<lv>30.00%</>攻击力的咒系伤害。\r\n喋喋不休：尖锐刻薄的话语如荆棘般不断刺穿目标，对目标连续造成6次基础伤害为<lv>20.00%</>攻击力的咒系伤害，最后一次攻击造成双倍伤害。",
        "buff_fork_jingmotingyuan_effect3": "装备者在未受到伤害的情况下降低血量后<lv>5</>秒内获得<lv>24.00%</>暴击伤害提高，至多叠加4次；可使用调弧·「静默庭园」\r\n调弧·「静默庭园」：扣除自身<lv>5.00%</>当前生命值，随机释放以下一种攻击（冷却时间<lv>25</>秒）：\r\n厉声呵斥：不留情面的呵斥如暴雨中的落叶接二连三，对目标造成5次<lv>36.00%</>攻击力的咒系伤害。\r\n喋喋不休：尖锐刻薄的话语如荆棘般不断刺穿目标，对目标连续造成6次基础伤害为<lv>24.00%</>攻击力的咒系伤害，最后一次攻击造成双倍伤害。",
        "buff_fork_jingmotingyuan_effect4": "装备者在未受到伤害的情况下降低血量后<lv>5</>秒内获得<lv>28.00%</>暴击伤害提高，至多叠加4次；可使用调弧·「静默庭园」\r\n调弧·「静默庭园」：扣除自身<lv>5.00%</>当前生命值，随机释放以下一种攻击（冷却时间<lv>25</>秒）：\r\n厉声呵斥：不留情面的呵斥如暴雨中的落叶接二连三，对目标造成5次<lv>42.00%</>攻击力的咒系伤害。\r\n喋喋不休：尖锐刻薄的话语如荆棘般不断刺穿目标，对目标连续造成6次基础伤害为<lv>28.00%</>攻击力的咒系伤害，最后一次攻击造成双倍伤害。",
        "buff_fork_jingmotingyuan_effect5": "装备者在未受到伤害的情况下降低血量后<lv>5</>秒内获得<lv>32.00%</>暴击伤害提高，至多叠加4次；可使用调弧·「静默庭园」\r\n调弧·「静默庭园」：扣除自身<lv>5.00%</>当前生命值，随机释放以下一种攻击（冷却时间<lv>25</>秒）：\r\n厉声呵斥：不留情面的呵斥如暴雨中的落叶接二连三，对目标造成5次<lv>48.00%</>攻击力的咒系伤害。\r\n喋喋不休：尖锐刻薄的话语如荆棘般不断刺穿目标，对目标连续造成6次基础伤害为<lv>32.00%</>攻击力的咒系伤害，最后一次攻击造成双倍伤害。",
        "buff_fork_oulaquantao_effect1": "装备者每次「普通攻击」后<lv>10</>秒内，自身「普通攻击」伤害提高<lv>2.50%</>，最多叠加10层。",
        "buff_fork_oulaquantao_effect2": "装备者每次「普通攻击」后<lv>10</>秒内，自身「普通攻击」伤害提高<lv>2.90%</>，最多叠加10层。",
        "buff_fork_oulaquantao_effect3": "装备者每次「普通攻击」后<lv>10</>秒内，自身「普通攻击」伤害提高<lv>3.30%</>，最多叠加10层。",
        "buff_fork_oulaquantao_effect4": "装备者每次「普通攻击」后<lv>10</>秒内，自身「普通攻击」伤害提高<lv>3.70%</>，最多叠加10层。",
        "buff_fork_oulaquantao_effect5": "装备者每次「普通攻击」后<lv>10</>秒内，自身「普通攻击」伤害提高<lv>4.00%</>，最多叠加10层。",
        "buff_fork_lingganzhongjiezhe_effect1": "装备者释放「变轨攻击」后，自身获得<lv>6</>点场域原质，该效果每<lv>20</>秒最多触发一次。",
        "buff_fork_lingganzhongjiezhe_effect2": "装备者释放「变轨攻击」后，自身获得<lv>7</>点场域原质，该效果每<lv>20</>秒最多触发一次。",
        "buff_fork_lingganzhongjiezhe_effect3": "装备者释放「变轨攻击」后，自身获得<lv>8</>点场域原质，该效果每<lv>20</>秒最多触发一次。",
        "buff_fork_lingganzhongjiezhe_effect4": "装备者释放「变轨攻击」后，自身获得<lv>9</>点场域原质，该效果每<lv>20</>秒最多触发一次。",
        "buff_fork_lingganzhongjiezhe_effect5": "装备者释放「变轨攻击」后，自身获得<lv>10</>点场域原质，该效果每<lv>20</>秒最多触发一次。",
        "buff_fork_rishi_effect1": "装备者的攻击力提升<lv>30.00%</>，可使用调弧·「日蚀」。\n调弧·「日蚀」：装备者可暂时利用日蚀的能力创造一场持续<lv>40</>秒的日蚀。在日蚀持续期间，装备者每击杀一名敌方单位可恢复<lv>2</>点场域原质，持续时间内最多触发<lv>5</>次。(冷却时间<lv>300</>秒)。",
        "buff_fork_rishi_effect2": "装备者的攻击力提升<lv>37.50%</>，可使用调弧·「日蚀」。\n调弧·「日蚀」：装备者可暂时利用日蚀的能力创造一场持续<lv>40</>秒的日蚀。在日蚀持续期间，装备者每击杀一名敌方单位可恢复<lv>2.5</>点场域原质，持续时间内最多触发<lv>5</>次。(冷却时间<lv>300</>秒)。",
        "buff_fork_rishi_effect3": "装备者的攻击力提升<lv>45.00%</>，可使用调弧·「日蚀」。\n调弧·「日蚀」：装备者可暂时利用日蚀的能力创造一场持续<lv>40</>秒的日蚀。在日蚀持续期间，装备者每击杀一名敌方单位可恢复<lv>3</>点场域原质，持续时间内最多触发<lv>5</>次。(冷却时间<lv>300</>秒)。",
        "buff_fork_rishi_effect4": "装备者的攻击力提升<lv>52.50%</>，可使用调弧·「日蚀」。\n调弧·「日蚀」：装备者可暂时利用日蚀的能力创造一场持续<lv>40</>秒的日蚀。在日蚀持续期间，装备者每击杀一名敌方单位可恢复<lv>3.5</>点场域原质，持续时间内最多触发<lv>5</>次。(冷却时间<lv>300</>秒)。",
        "buff_fork_rishi_effect5": "装备者的攻击力提升<lv>60.00%</>，可使用调弧·「日蚀」。\n调弧·「日蚀」：装备者可暂时利用日蚀的能力创造一场持续<lv>40</>秒的日蚀。在日蚀持续期间，装备者每击杀一名敌方单位可恢复<lv>4</>点场域原质，持续时间内最多触发<lv>5</>次。(冷却时间<lv>300</>秒)。",
        "buff_fork_dustbin_effect1": "装备者积累倾陷值时，自身提高<lv>40</>倾陷强度，持续<lv>10</>秒，<lv>20</>秒内最多触发一次。",
        "buff_fork_dustbin_effect2": "装备者积累倾陷值时，自身提高<lv>46</>倾陷强度，持续<lv>10</>秒，<lv>20</>秒内最多触发一次。",
        "buff_fork_dustbin_effect3": "装备者积累倾陷值时，自身提高<lv>52</>倾陷强度，持续<lv>10</>秒，<lv>20</>秒内最多触发一次。",
        "buff_fork_dustbin_effect4": "装备者积累倾陷值时，自身提高<lv>58</>倾陷强度，持续<lv>10</>秒，<lv>20</>秒内最多触发一次。",
        "buff_fork_dustbin_effect5": "装备者积累倾陷值时，自身提高<lv>64</>倾陷强度，持续<lv>10</>秒，<lv>20</>秒内最多触发一次。",
        "buff_fork_nonos_effect1": "装备者释放「变轨攻击」后，自身攻击力提升<lv>15.00%</>，持续<lv>10</>秒，<lv>20</>秒内最多触发一次。",
        "buff_fork_nonos_effect2": "装备者释放「变轨攻击」后，自身攻击力提升<lv>17.00%</>，持续<lv>10</>秒，<lv>20</>秒内最多触发一次。",
        "buff_fork_nonos_effect3": "装备者释放「变轨攻击」后，自身攻击力提升<lv>19.00%</>，持续<lv>10</>秒，<lv>20</>秒内最多触发一次。",
        "buff_fork_nonos_effect4": "装备者释放「变轨攻击」后，自身攻击力提升<lv>21.00%</>，持续<lv>10</>秒，<lv>20</>秒内最多触发一次。",
        "buff_fork_nonos_effect5": "装备者释放「变轨攻击」后，自身攻击力提升<lv>24.00%</>，持续<lv>10</>秒，<lv>20</>秒内最多触发一次。",
        "buff_fork_vine_effect1": "装备者击杀敌人时，回复自身<lv>12.00%</>生命值，<lv>20</>秒内最多触发一次。",
        "buff_fork_vine_effect2": "装备者击杀敌人时，回复自身<lv>14.00%</>生命值，<lv>20</>秒内最多触发一次。",
        "buff_fork_vine_effect3": "装备者击杀敌人时，回复自身<lv>16.00%</>生命值，<lv>20</>秒内最多触发一次。",
        "buff_fork_vine_effect4": "装备者击杀敌人时，回复自身<lv>18.00%</>生命值，<lv>20</>秒内最多触发一次。",
        "buff_fork_vine_effect5": "装备者击杀敌人时，回复自身<lv>20.00%</>生命值，<lv>20</>秒内最多触发一次。",
        "buff_fork_Prokaryon_effect1": "装备者「普通攻击」造成的伤害提高<lv>10.00%</>。",
        "buff_fork_Prokaryon_effect2": "装备者「普通攻击」造成的伤害提高<lv>11.50%</>。",
        "buff_fork_Prokaryon_effect3": "装备者「普通攻击」造成的伤害提高<lv>13.00%</>。",
        "buff_fork_Prokaryon_effect4": "装备者「普通攻击」造成的伤害提高<lv>14.50%</>。",
        "buff_fork_Prokaryon_effect5": "装备者「普通攻击」造成的伤害提高<lv>16.00%</>。",
        "buff_fork_BitterCake_effect1": "装备者收到攻击时，自身防御力提高<lv>30.00%</>，持续<lv>10</>秒，<lv>20</>秒内最多触发一次。",
        "buff_fork_BitterCake_effect2": "装备者收到攻击时，自身防御力提高<lv>34.00%</>，持续<lv>10</>秒，<lv>20</>秒内最多触发一次。",
        "buff_fork_BitterCake_effect3": "装备者收到攻击时，自身防御力提高<lv>39.00%</>，持续<lv>10</>秒，<lv>20</>秒内最多触发一次。",
        "buff_fork_BitterCake_effect4": "装备者收到攻击时，自身防御力提高<lv>44.00%</>，持续<lv>10</>秒，<lv>20</>秒内最多触发一次。",
        "buff_fork_BitterCake_effect5": "装备者收到攻击时，自身防御力提高<lv>48.00%</>，持续<lv>10</>秒，<lv>20</>秒内最多触发一次。",
        "buff_fork_appliance_effect1": "装备者「变轨攻击」造成的伤害提高<lv>10.00%</>。",
        "buff_fork_appliance_effect2": "装备者「变轨攻击」造成的伤害提高<lv>11.50%</>。",
        "buff_fork_appliance_effect3": "装备者「变轨攻击」造成的伤害提高<lv>13.00%</>。",
        "buff_fork_appliance_effect4": "装备者「变轨攻击」造成的伤害提高<lv>14.50%</>。",
        "buff_fork_appliance_effect5": "装备者「变轨攻击」造成的伤害提高<lv>16.00%</>。",
        "buff_fork_TigerTally_effect1": "装备者的攻击力提高<lv>16.00%</>，释放「变轨攻击」或「极轨终结」时，「普通攻击」造成伤害提升<lv>16.00%</>，持续<lv>15</>秒，该效果最多叠加两层。\n装备者释放「变轨攻击」时可以获得\"左虎符\"，释放「极轨终结」时，可以获得\"右虎符\"。若在获得一种虎符的<lv>15</>秒内获得另一种虎符，则会获得「预备备」，同时可使用调弧：「司令虎符」。\n调弧·「司令虎符」：装备者对Boss单位造成的伤害提升<lv>10.00%</>，持续<lv>10</>秒。",
        "buff_fork_TigerTally_effect2": "装备者的攻击力提高<lv>20.00%</>，释放「变轨攻击」或「极轨终结」时，「普通攻击」造成伤害提升<lv>20.00%</>，持续<lv>15</>秒，该效果最多叠加两层。\n装备者释放「变轨攻击」时可以获得\"左虎符\"，释放「极轨终结」时，可以获得\"右虎符\"。若在获得一种虎符的<lv>15</>秒内获得另一种虎符，则会获得「预备备」，同时可使用调弧：「司令虎符」。\n调弧·「司令虎符」：装备者对Boss单位造成的伤害提升<lv>12.50%</>，持续<lv>10</>秒。",
        "buff_fork_TigerTally_effect3": "装备者的攻击力提高<lv>24.00%</>，释放「变轨攻击」或「极轨终结」时，「普通攻击」造成伤害提升<lv>24.00%</>，持续<lv>15</>秒，该效果最多叠加两层。\n装备者释放「变轨攻击」时可以获得\"左虎符\"，释放「极轨终结」时，可以获得\"右虎符\"。若在获得一种虎符的<lv>15</>秒内获得另一种虎符，则会获得「预备备」，同时可使用调弧：「司令虎符」。\n调弧·「司令虎符」：装备者对Boss单位造成的伤害提升<lv>15.00%</>，持续<lv>10</>秒。",
        "buff_fork_TigerTally_effect4": "装备者的攻击力提高<lv>28.00%</>，释放「变轨攻击」或「极轨终结」时，「普通攻击」造成伤害提升<lv>28.00%</>，持续<lv>15</>秒，该效果最多叠加两层。\n装备者释放「变轨攻击」时可以获得\"左虎符\"，释放「极轨终结」时，可以获得\"右虎符\"。若在获得一种虎符的<lv>15</>秒内获得另一种虎符，则会获得「预备备」，同时可使用调弧：「司令虎符」。\n调弧·「司令虎符」：装备者对Boss单位造成的伤害提升<lv>17.50%</>，持续<lv>10</>秒。",
        "buff_fork_TigerTally_effect5": "装备者的攻击力提高<lv>32.00%</>，释放「变轨攻击」或「极轨终结」时，「普通攻击」造成伤害提升<lv>32.00%</>，持续<lv>15</>秒，该效果最多叠加两层。\n装备者释放「变轨攻击」时可以获得\"左虎符\"，释放「极轨终结」时，可以获得\"右虎符\"。若在获得一种虎符的<lv>15</>秒内获得另一种虎符，则会获得「预备备」，同时可使用调弧：「司令虎符」。\n调弧·「司令虎符」：装备者对Boss单位造成的伤害提升<lv>20.00%</>，持续<lv>10</>秒。",
        "buff_fork_BitGame_effect1": "装备者位于后台的时候，每<lv>3</>秒获得<lv>32</>点原质驱力，最多叠加6层。当被切换至前场<lv>5</>秒后或者再次切换至后台时候，获得的原质驱力清零。",
        "buff_fork_BitGame_effect2": "装备者位于后台的时候，每<lv>3</>秒获得<lv>40</>点原质驱力，最多叠加6层。当被切换至前场<lv>5</>秒后或者再次切换至后台时候，获得的原质驱力清零。",
        "buff_fork_BitGame_effect3": "装备者位于后台的时候，每<lv>3</>秒获得<lv>48</>点原质驱力，最多叠加6层。当被切换至前场<lv>5</>秒后或者再次切换至后台时候，获得的原质驱力清零。",
        "buff_fork_BitGame_effect4": "装备者位于后台的时候，每<lv>3</>秒获得<lv>56</>点原质驱力，最多叠加6层。当被切换至前场<lv>5</>秒后或者再次切换至后台时候，获得的原质驱力清零。",
        "buff_fork_BitGame_effect5": "装备者位于后台的时候，每<lv>3</>秒获得<lv>64</>点原质驱力，最多叠加6层。当被切换至前场<lv>5</>秒后或者再次切换至后台时候，获得的原质驱力清零。",
        "buff_fork_BlackBook_effect1": "装备者的攻击力提高<lv>10.00%</>。\n常态下调弧·「黑之书」被六根锁链封锁，每当装备者进行极限闪避、承轨反击、协同技和变轨攻击时可解除一根锁链。六根锁链全部解除后可使用调弧·「黑之书」。\n调弧·「黑之书」：召唤黑之书持续链接敌人，被链接的敌人暗系抗性减少<lv>20.00%</>，最多链接六个敌人，持续<lv>30</>秒。",
        "buff_fork_BlackBook_effect2": "装备者的攻击力提高<lv>12.50%</>。\r\n常态下调弧·「黑之书」被六根锁链封锁，每当装备者进行极限闪避、承轨反击、协同技和变轨攻击时可解除一根锁链。六根锁链全部解除后可使用调弧·「黑之书」。\r\n调弧·「黑之书」：召唤黑之书持续链接敌人，被链接的敌人暗系抗性减少<lv>25.00%</>，最多链接六个敌人，持续<lv>30</>秒。",
        "buff_fork_BlackBook_effect3": "装备者的攻击力提高<lv>15.00%</>。\n常态下调弧·「黑之书」被六根锁链封锁，每当装备者进行极限闪避、承轨反击、协同技和变轨攻击时可解除一根锁链。六根锁链全部解除后可使用调弧·「黑之书」。\n调弧·「黑之书」：召唤黑之书持续链接敌人，被链接的敌人暗系抗性减少<lv>30.00%</>，最多链接六个敌人，持续<lv>30</>秒。",
        "buff_fork_BlackBook_effect4": "装备者的攻击力提高<lv>17.50%</>。\n常态下调弧·「黑之书」被六根锁链封锁，每当装备者进行极限闪避、承轨反击、协同技和变轨攻击时可解除一根锁链。六根锁链全部解除后可使用调弧·「黑之书」。\n调弧·「黑之书」：召唤黑之书持续链接敌人，被链接的敌人暗系抗性减少<lv>35.00%</>，最多链接六个敌人，持续<lv>30</>秒。",
        "buff_fork_BlackBook_effect5": "装备者的攻击力提高<lv>20.00%</>。\n常态下调弧·「黑之书」被六根锁链封锁，每当装备者进行极限闪避、承轨反击、协同技和变轨攻击时可解除一根锁链。六根锁链全部解除后可使用调弧·「黑之书」。\n调弧·「黑之书」：召唤黑之书持续链接敌人，被链接的敌人暗系抗性减少<lv>40.00%</>，最多链接六个敌人，持续<lv>30</>秒。",
        "buff_fork_mamen_effect1": "装备者每持有<lv>100000</>方斯，攻击力提高<lv>5.00%</>，最多叠加10层。",
        "buff_fork_mamen_effect2": "装备者每持有<lv>100000</>方斯，攻击力提高<lv>6.25%</>，最多叠加10层。",
        "buff_fork_mamen_effect3": "装备者每持有<lv>100000</>方斯，攻击力提高<lv>7.50%</>，最多叠加10层。",
        "buff_fork_mamen_effect4": "装备者每持有<lv>100000</>方斯，攻击力提高<lv>8.75%</>，最多叠加10层。",
        "buff_fork_mamen_effect5": "装备者每持有<lv>100000</>方斯，攻击力提高<lv>10.00%</>，最多叠加10层。",
        "buff_fork_Nakupeda_effect1": "生命值提高<lv>20.00%</>。\n装备者释放「极轨终结」时，获得以下随机一个效果：\n1.使队伍中血量百分比最低的角色回复其<lv>20.00%</>最大生命值。\n2.获得一个装备者<lv>20.00%</>最大生命值的护盾,持续<lv>15</>秒。\n3.使全队角色回复<lv>10.00%</>生命值。\n该效果每<lv>30</>秒最多触发一次。",
        "buff_fork_Nakupeda_effect2": "生命值提高<lv>25.00%</>。\n装备者释放「极轨终结」时，获得以下随机一个效果：\n1.使队伍中血量百分比最低的角色回复其<lv>25.00%</>最大生命值。\n2.获得一个装备者<lv>25.00%</>最大生命值的护盾,持续<lv>15</>秒。\n3.使全队角色回复<lv>12.50%</>生命值。\n该效果每<lv>30</>秒最多触发一次。",
        "buff_fork_Nakupeda_effect3": "生命值提高<lv>30.00%</>。\n装备者释放「极轨终结」时，获得以下随机一个效果：\n1.使队伍中血量百分比最低的角色回复其<lv>30.00%</>最大生命值。\n2.获得一个装备者<lv>30.00%</>最大生命值的护盾,持续<lv>15</>秒。\n3.使全队角色回复<lv>15.00%</>生命值。\n该效果每<lv>30</>秒最多触发一次。",
        "buff_fork_Nakupeda_effect4": "生命值提高<lv>35.00%</>。\n装备者释放「极轨终结」时，获得以下随机一个效果：\n1.使队伍中血量百分比最低的角色回复其<lv>35.00%</>最大生命值。\n2.获得一个装备者<lv>35.00%</>最大生命值的护盾,持续<lv>15</>秒。\n3.使全队角色回复<lv>17.50%</>生命值。\n该效果每<lv>30</>秒最多触发一次。",
        "buff_fork_Nakupeda_effect5": "生命值提高<lv>40.00%</>。\n装备者释放「极轨终结」时，获得以下随机一个效果：\n1.使队伍中血量百分比最低的角色回复其<lv>40.00%</>最大生命值。\n2.获得一个装备者<lv>40.00%</>最大生命值的护盾,持续<lv>15</>秒。\n3.使全队角色回复<lv>20.00%</>生命值。\n该效果每<lv>30</>秒最多触发一次。",
        "buff_fork_wushoutieyu_effect1": "释放「极轨终结」后，装备者「变轨攻击」造成伤害提升<lv>30.00%</>，持续<lv>10</>秒。在该效果生效时，每次释放「变轨攻击」时，装备者的「变轨攻击」造成伤害提升<lv>15.00%</>，通过这一方式获得的伤害提升最多叠加两次。",
        "buff_fork_wushoutieyu_effect2": "释放「极轨终结」后，装备者「变轨攻击」造成伤害提升<lv>38.00%</>，持续<lv>10</>秒。在该效果生效时，每次释放「变轨攻击」时，装备者的「变轨攻击」造成伤害提升<lv>18.00%</>，通过这一方式获得的伤害提升最多叠加两次。",
        "buff_fork_wushoutieyu_effect3": "释放「极轨终结」后，装备者「变轨攻击」造成伤害提升<lv>45.00%</>，持续<lv>10</>秒。在该效果生效时，每次释放「变轨攻击」时，装备者的「变轨攻击」造成伤害提升<lv>22.00%</>，通过这一方式获得的伤害提升最多叠加两次。",
        "buff_fork_wushoutieyu_effect4": "释放「极轨终结」后，装备者「变轨攻击」造成伤害提升<lv>53.00%</>，持续<lv>10</>秒。在该效果生效时，每次释放「变轨攻击」时，装备者的「变轨攻击」造成伤害提升<lv>26.00%</>，通过这一方式获得的伤害提升最多叠加两次。",
        "buff_fork_wushoutieyu_effect5": "释放「极轨终结」后，装备者「变轨攻击」造成伤害提升<lv>60.00%</>，持续<lv>10</>秒。在该效果生效时，每次释放「变轨攻击」时，装备者的「变轨攻击」造成伤害提升<lv>30.00%</>，通过这一方式获得的伤害提升最多叠加两次。",
        "buff_fork_Arachne_effect1": "生命值提高<lv>25.00%</>。\n装备者释放「极轨终结」以后，自身造成的潜意伤害提高<lv>20.00%</>，持续<lv>10</>秒。",
        "buff_fork_Arachne_effect2": "生命值提高<lv>32.00%</>。\n装备者释放「极轨终结」以后，自身造成的潜意伤害提高<lv>25.00%</>，持续<lv>10</>秒。",
        "buff_fork_Arachne_effect3": "生命值提高<lv>38.00%</>。\n装备者释放「极轨终结」以后，自身造成的潜意伤害提高<lv>30.00%</>，持续<lv>10</>秒。",
        "buff_fork_Arachne_effect4": "生命值提高<lv>44.00%</>。\n装备者释放「极轨终结」以后，自身造成的潜意伤害提高<lv>35.00%</>，持续<lv>10</>秒。",
        "buff_fork_Arachne_effect5": "生命值提高<lv>50.00%</>。\n装备者释放「极轨终结」以后，自身造成的潜意伤害提高<lv>40.00%</>，持续<lv>10</>秒。",
        "buff_fork_PoliceRat_effect1": "攻击力提高<lv>20.00%</>。\n装备者对Boss单位造成的伤害提高<lv>20.00%</>。",
        "buff_fork_PoliceRat_effect2": "攻击力提高<lv>25.00%</>。\n装备者对Boss单位造成的伤害提高<lv>25.00%</>。",
        "buff_fork_PoliceRat_effect3": "攻击力提高<lv>30.00%</>。\n装备者对Boss单位造成的伤害提高<lv>30.00%</>。",
        "buff_fork_PoliceRat_effect4": "攻击力提高<lv>35.00%</>。\n装备者对Boss单位造成的伤害提高<lv>35.00%</>。",
        "buff_fork_PoliceRat_effect5": "攻击力提高<lv>40.00%</>。\n装备者对Boss单位造成的伤害提高<lv>40.00%</>。",
        "buff_fork_tuansanlang_effect1": "当队伍中与装备者相同异能系谱的角色数量大于等于3个(包含自身)，该异能系谱角色们均提升<lv>80</>倾陷强度，该效果同时仅能生效一次。",
        "buff_fork_tuansanlang_effect2": "当队伍中与装备者相同异能系谱的角色数量大于等于3个(包含自身)，该异能系谱角色们均提升<lv>92</>倾陷强度，该效果同时仅能生效一次。",
        "buff_fork_tuansanlang_effect3": "当队伍中与装备者相同异能系谱的角色数量大于等于3个(包含自身)，该异能系谱角色们均提升<lv>104</>倾陷强度，该效果同时仅能生效一次。",
        "buff_fork_tuansanlang_effect4": "当队伍中与装备者相同异能系谱的角色数量大于等于3个(包含自身)，该异能系谱角色们均提升<lv>116</>倾陷强度，该效果同时仅能生效一次。",
        "buff_fork_tuansanlang_effect5": "当队伍中与装备者相同异能系谱的角色数量大于等于3个(包含自身)，该异能系谱角色们均提升<lv>128</>倾陷强度，该效果同时仅能生效一次。",
        "buff_fork_Kite_effect1": "装备者释放「变轨攻击」以后，自身攻击力提高<lv>12.00%</>，并且对于处于受到「延滞」和「浸染」影响的单位造成的相系伤害提高<lv>12.00%</>，持续<lv>15</>秒，该效果无法叠加。",
        "buff_fork_Kite_effect2": "装备者释放「变轨攻击」以后，自身攻击力提高<lv>14.00%</>，并且对于处于受到「延滞」和「浸染」影响的单位造成的相系伤害提高<lv>14.00%</>，持续<lv>15</>秒，该效果无法叠加。",
        "buff_fork_Kite_effect3": "装备者释放「变轨攻击」以后，自身攻击力提高<lv>16.00%</>，并且对于处于受到「延滞」和「浸染」影响的单位造成的相系伤害提高<lv>16.00%</>，持续<lv>15</>秒，该效果无法叠加。",
        "buff_fork_Kite_effect4": "装备者释放「变轨攻击」以后，自身攻击力提高<lv>18.00%</>，并且对于处于受到「延滞」和「浸染」影响的单位造成的相系伤害提高<lv>18.00%</>，持续<lv>15</>秒，该效果无法叠加。",
        "buff_fork_Kite_effect5": "装备者释放「变轨攻击」以后，自身攻击力提高<lv>20.00%</>，并且对于处于受到「延滞」和「浸染」影响的单位造成的相系伤害提高<lv>20.00%</>，持续<lv>15</>秒，该效果无法叠加。",
        "buff_fork_PaperPlane_effect1": "装备者的「变轨攻击」和「极轨终结」造成的灵系伤害提升<lv>20.00%</>。",
        "buff_fork_PaperPlane_effect2": "装备者的「变轨攻击」和「极轨终结」造成的灵系伤害提升<lv>23.00%</>。",
        "buff_fork_PaperPlane_effect3": "装备者的「变轨攻击」和「极轨终结」造成的灵系伤害提升<lv>26.00%</>。",
        "buff_fork_PaperPlane_effect4": "装备者的「变轨攻击」和「极轨终结」造成的灵系伤害提升<lv>29.00%</>。",
        "buff_fork_PaperPlane_effect5": "装备者的「变轨攻击」和「极轨终结」造成的灵系伤害提升<lv>32.00%</>。",
        "buff_fork_spider_effect1": "装备者通过「普通攻击」造成伤害可使自身获得1层「蜘识」，最多叠加8层，每0.5秒最多获得1层「蜘识」。装备者释放「极轨终结」时消耗所有「蜘识」，每消耗1层「蜘识」可以让全队在<lv>10</>秒内攻击力提升<lv>1.00%</>；若消耗的「蜘识」数量为8，则额外使全队攻击力提升<lv>2.00%</>。",
        "buff_fork_spider_effect2": "装备者通过「普通攻击」造成伤害可使自身获得1层「蜘识」，最多叠加8层，每0.5秒最多获得1层「蜘识」。装备者释放「极轨终结」时消耗所有「蜘识」，每消耗1层「蜘识」可以让全队在<lv>10</>秒内攻击力提升<lv>1.15%</>；若消耗的「蜘识」数量为8，则额外使全队攻击力提升<lv>2.30%</>。",
        "buff_fork_spider_effect3": "装备者通过「普通攻击」造成伤害可使自身获得1层「蜘识」，最多叠加8层，每0.5秒最多获得1层「蜘识」。装备者释放「极轨终结」时消耗所有「蜘识」，每消耗1层「蜘识」可以让全队在<lv>10</>秒内攻击力提升<lv>1.30%</>；若消耗的「蜘识」数量为8，则额外使全队攻击力提升<lv>2.60%</>。",
        "buff_fork_spider_effect4": "装备者通过「普通攻击」造成伤害可使自身获得1层「蜘识」，最多叠加8层，每0.5秒最多获得1层「蜘识」。装备者释放「极轨终结」时消耗所有「蜘识」，每消耗1层「蜘识」可以让全队在<lv>10</>秒内攻击力提升<lv>1.45%</>；若消耗的「蜘识」数量为8，则额外使全队攻击力提升<lv>2.90%</>。",
        "buff_fork_spider_effect5": "装备者通过「普通攻击」造成伤害可使自身获得1层「蜘识」，最多叠加8层，每0.5秒最多获得1层「蜘识」。装备者释放「极轨终结」时消耗所有「蜘识」，每消耗1层「蜘识」可以让全队在<lv>10</>秒内攻击力提升<lv>1.60%</>；若消耗的「蜘识」数量为8，则额外使全队攻击力提升<lv>3.20%</>。",
        "buff_fork_yaodao_effect1": "装备者触发「承轨反击」以后的下一次「普通攻击」附带一次<lv>200.00%</>攻击力的咒系伤害。",
        "buff_fork_yaodao_effect2": "装备者触发「承轨反击」以后的下一次「普通攻击」附带一次<lv>230.00%</>攻击力的咒系伤害。",
        "buff_fork_yaodao_effect3": "装备者触发「承轨反击」以后的下一次「普通攻击」附带一次<lv>260.00%</>攻击力的咒系伤害。",
        "buff_fork_yaodao_effect4": "装备者触发「承轨反击」以后的下一次「普通攻击」附带一次<lv>290.00%</>攻击力的咒系伤害。",
        "buff_fork_yaodao_effect5": "装备者触发「承轨反击」以后的下一次「普通攻击」附带一次<lv>320.00%</>攻击力的咒系伤害。",
        "buff_fork_koinobori_effect1": "当编队存在不少于3个不同异能系谱的时候，装备者获得<lv>20.00%</>攻击力，<lv>20.00%</>防御力，<lv>20.00%</>生命值。",
        "buff_fork_koinobori_effect2": "当编队存在不少于3个不同异能系谱的时候，装备者获得<lv>23.00%</>攻击力，<lv>23.00%</>防御力，<lv>23.00%</>生命值。",
        "buff_fork_koinobori_effect3": "当编队存在不少于3个不同异能系谱的时候，装备者获得<lv>26.00%</>攻击力，<lv>26.00%</>防御力，<lv>26.00%</>生命值。",
        "buff_fork_koinobori_effect4": "当编队存在不少于3个不同异能系谱的时候，装备者获得<lv>29.00%</>攻击力，<lv>29.00%</>防御力，<lv>29.00%</>生命值。",
        "buff_fork_koinobori_effect5": "当编队存在不少于3个不同异能系谱的时候，装备者获得<lv>32.00%</>攻击力，<lv>32.00%</>防御力，<lv>32.00%</>生命值。",
        "buff_fork_snowman_effect1": "当装备者具有护盾的时候，攻击力提升<lv>20.00%</>。",
        "buff_fork_snowman_effect2": "当装备者具有护盾的时候，攻击力提升<lv>23.00%</>。",
        "buff_fork_snowman_effect3": "当装备者具有护盾的时候，攻击力提升<lv>26.00%</>。",
        "buff_fork_snowman_effect4": "当装备者具有护盾的时候，攻击力提升<lv>29.00%</>。",
        "buff_fork_snowman_effect5": "当装备者具有护盾的时候，攻击力提升<lv>32.00%</>。",
        "buff_fork_dustbin_name": "「分解者」",
        "buff_fork_nonos_name": "「诺诺斯」",
        "buff_fork_vine_name": "「抱抱藤」",
        "buff_fork_Prokaryon_name": "「原核体」",
        "buff_fork_tuansanlang_name": "「团三郎」",
        "buff_fork_BitterCake_name": "「苦蛋糕」",
        "buff_fork_Kite_name": "「诡面筝」",
        "buff_fork_PaperPlane_name": "「纸翼战队」",
        "buff_fork_appliance_name": "「附电灵」",
        "buff_fork_spider_name": "「蜘识藏家」",
        "buff_fork_yaodao_name": "「血染妖刀」",
        "buff_fork_koinobori_name": "「起潮洄天」",
        "buff_fork_BitGame_name": "「音霸魔王」",
        "buff_fork_mamen_name": "「玛门」",
        "buff_fork_BlackBook_name": "「黑之书」",
        "buff_fork_Arachne_name": "「阿拉克涅」",
        "buff_fork_PoliceRat_name": "「通行正义」",
        "buff_fork_Nakupeda_name": "「纳库佩达」",
        "buff_fork_snowman_name": "「夏刑草」",
        "buff_fork_TigerTally_name": "「司令虎符」",
        "fork_type_decorate_front": "「",
        "fork_type_decorate_back": "」",
        "fork_skill": "弧盘效果"
      },
      "KeysToMetaData": {}
    }
  }
]