[
  {
    "Type": "StringTable",
    "Name": "ST_Shop",
    "Class": "UScriptClass'StringTable'",
    "Flags": "RF_Public | RF_Standalone | RF_Transactional | RF_WasLoaded | RF_LoadCompleted",
    "StringTable": {
      "TableNamespace": "ST_shop",
      "KeysToEntries": {
        "gachashop_01_name": "扭蛋机兑换商店",
        "VendingMachine_000_name": "塔吉多的售货机",
        "VendingMachine_001_name": "售货机",
        "VendingMachine_002_name": "畅爽专卖售货机",
        "VendingMachine_003_name": "咕比奇专卖售货机",
        "VendingMachine_004_name": "鲍勃叔叔专卖售货机",
        "VendingMachine_005_name": "噗卡糖果专卖售货机",
        "VendingMachine_006_name": "番茄百分百专卖售货机",
        "Shop_001_01": "茂藏家豆腐店",
        "Shop_001_02": "夏成豆腐店",
        "Shop_002_01": "普利姆叔叔的肉铺",
        "Shop_003_01": "蔬菜屋",
        "Shop_004_01": "Myosotis水果铺",
        "Shop_005_01": "7-Oceans海鲜店",
        "Shop_006_01": "卜多力日料店",
        "Shop_006_02": "千酿鲜吟屋",
        "Shop_007_01": "2-Four便利店",
        "Shop_008_01": "噗卡糖果店",
        "Shop_009_01": "咔叽玛快食",
        "Shop_010_01": "集山忘野花店",
        "Shop_011_01": "爱丽丝烘焙坊",
        "Shop_012_01": "竹本清源药妆店",
        "Shop_013_01": "Exile on Main St.唱片店",
        "Shop_014_01": "月亮湾水族店",
        "Shop_015_01": "A.R.P.T.S阿普斯Bar",
        "Shop_016_01": "CrazyCat奶茶铺",
        "Shop_017_01": "FelicitàGelato冰淇淋店",
        "Shop_018_01": "滚岩烧烤铺",
        "Shop_019_01": "巨嘴包子铺",
        "Shop_020_01": "猫丸拉面铺",
        "Shop_021_01": "玛雷尼披萨餐厅",
        "Shop_023_01": "DSD潮玩",
        "Shop_024_01": "迈达斯科技",
        "Shop_025_01": "白鲸书店",
        "Shop_026_01": "植愈绿植店",
        "Shop_027_01": "鼎记烤鸭铺",
        "Shop_028_01": "9度咖啡馆",
        "Shop_029_01": "布朗二手电器",
        "Shop_030_01": "超规格家饰馆",
        "Shop_031_01": "Oops！Chest 惊喜匣子礼品店",
        "Shop_032_01": "阿克拉托斯-咖啡豆店",
        "Shop_033_01": "日常系-百味坊-副食品店",
        "Shop_034_01": "天下一品章鱼烧-章鱼小丸子铺",
        "Shop_035_01": "NewWay-车行",
        "Shop_035_02": "TerraX-车行",
        "Shop_035_03": "Regalia-车行",
        "Shop_036_01": "Ticking Back-单车店",
        "": ""
      },
      "KeysToMetaData": {}
    }
  }
]