[
  {
    "Type": "DataTable",
    "Name": "DT_DollData",
    "Class": "UScriptClass'DataTable'",
    "Flags": "RF_Public | RF_Standalone | RF_Transactional | RF_WasLoaded | RF_LoadCompleted",
    "Properties": {
      "RowStruct": {
        "ObjectName": "Class'StaticDollData'",
        "ObjectPath": "/Script/HTGame"
      }
    },
    "Rows": {
      "Doll_Huili": {
        "GroupId": "Doll_Huili",
        "ItemID": "Doll_Huili",
        "DollActorClass": {
          "AssetPathName": "/Game/Blueprints/Level/World/Common/ClawMachine/Doll/Huili/BP_Doll_Huili.BP_Doll_Huili_C",
          "SubPathString": ""
        },
        "ResultScale": {
          "X": 0.8,
          "Y": 0.8,
          "Z": 0.8
        }
      },
      "Doll_Rider": {
        "GroupId": "Doll_Rider",
        "ItemID": "Doll_Rider",
        "DollActorClass": {
          "AssetPathName": "/Game/Blueprints/Level/World/Common/ClawMachine/Doll/Rider/BP_Doll_Rider.BP_Doll_Rider_C",
          "SubPathString": ""
        },
        "ResultScale": {
          "X": 0.8,
          "Y": 0.8,
          "Z": 0.8
        }
      },
      "Doll_LonelyDoll": {
        "GroupId": "Doll_LonelyDoll",
        "ItemID": "Doll_LonelyDoll",
        "DollActorClass": {
          "AssetPathName": "/Game/Blueprints/Level/World/Common/ClawMachine/Doll/LonelyDoll/BP_Doll_LonelyDoll.BP_Doll_LonelyDoll_C",
          "SubPathString": ""
        },
        "ResultScale": {
          "X": 0.8,
          "Y": 0.8,
          "Z": 0.8
        }
      },
      "Doll_PoliceMouse": {
        "GroupId": "Doll_PoliceMouse",
        "ItemID": "Doll_PoliceMouse",
        "DollActorClass": {
          "AssetPathName": "/Game/Blueprints/Level/World/Common/ClawMachine/Doll/policemouse/BP_Doll_Policemouse.BP_Doll_Policemouse_C",
          "SubPathString": ""
        },
        "ResultScale": {
          "X": 0.8,
          "Y": 0.8,
          "Z": 0.8
        }
      }
    }
  }
]